README.md
setup.py
LibcSearcher/LibcSearcher.py
LibcSearcher/__init__.py
LibcSearcher.egg-info/PKG-INFO
LibcSearcher.egg-info/SOURCES.txt
LibcSearcher.egg-info/dependency_links.txt
LibcSearcher.egg-info/requires.txt
LibcSearcher.egg-info/top_level.txt