Metadata-Version: 2.1
Name: LibcSearcher
Version: 1.1.5
Summary: Python wrapper for libc-database.
Home-page: https://github.com/IZAY01/LibcSearcher
Author: IZAY01
Author-email: IZAYOInt0x80@gmail.com
License: BSD
Platform: any
